{"team_1": {"team_name": "India", "athlete_info_list": [{"age_days": "271", "age_years": "24", "alpha_name": "KARTHIK,KD", "batting_hand": "right-hand batsman", "batting_style": "rhb", "batting_style_long": "right-hand bat", "bowling_hand": "unknown arm", "bowling_pacespin": "mixture/unknown", "bowling_style": null, "bowling_style_long": null, "captain": "0", "card_long": "KD Karthik", "card_qualifier": "", "card_short": "Karthik", "dob": "1985-06-01", "keeper": "0", "known_as": "Dinesh Karthik", "mobile_name": "Karthik", "object_id": "30045", "player_id": "8813", "player_primary_role": "wicketkeeper batsman", "player_style_id": "7", "player_type": "1", "player_type_name": "player", "popular_name": "Karthik", "portrait_alt_id": "1", "portrait_object_id": "1099909", "status_id": "3"}, {"age_days": "332", "age_years": "25", "alpha_name": "VIJAY,M", "batting_hand": "right-hand batsman", "batting_style": "rhb", "batting_style_long": "right-hand bat", "bowling_hand": "right-arm bowler", "bowling_pacespin": "spin bowler", "bowling_style": "ob", "bowling_style_long": "right-arm offbreak ", "captain": "0", "card_long": "M Vijay", "card_qualifier": "", "card_short": "Vijay", "dob": "1984-04-01", "keeper": "0", "known_as": "Murali Vijay", "mobile_name": "Vijay", "object_id": "237095", "player_id": "49342", "player_primary_role": "opening batsman", "player_style_id": "1", "player_type": "1", "player_type_name": "player", "popular_name": "Vijay", "portrait_alt_id": "1", "portrait_object_id": "817497", "status_id": "3"}, {"age_days": "114", "age_years": "21", "alpha_name": "KOHLI,V", "batting_hand": "right-hand batsman", "batting_style": "rhb", "batting_style_long": "right-hand bat", "bowling_hand": "right-arm bowler", "bowling_pacespin": "pace bowler", "bowling_style": "rm", "bowling_style_long": "right-arm medium ", "captain": "0", "card_long": "V Kohli", "card_qualifier": "", "card_short": "Kohli", "dob": "1988-11-05", "keeper": "0", "known_as": "Virat Kohli", "mobile_name": "Kohli", "object_id": "253802", "player_id": "49752", "player_primary_role": "top-order batsman", "player_style_id": "2", "player_type": "1", "player_type_name": "player", "popular_name": "Kohli", "portrait_alt_id": "1", "portrait_object_id": "1183835", "status_id": "3"}, {"age_days": "303", "age_years": "22", "alpha_name": "SHARMA,RG", "batting_hand": "right-hand batsman", "batting_style": "rhb", "batting_style_long": "right-hand bat", "bowling_hand": "right-arm bowler", "bowling_pacespin": "spin bowler", "bowling_style": "ob", "bowling_style_long": "right-arm offbreak ", "captain": "0", "card_long": "RG Sharma", "card_qualifier": "", "card_short": "Sharma", "dob": "1987-04-30", "keeper": "0", "known_as": "Rohit Sharma", "mobile_name": "Rohit", "object_id": "34102", "player_id": "48405", "player_primary_role": "top-order batsman", "player_style_id": "2", "player_type": "1", "player_type_name": "player", "popular_name": "Rohit", "portrait_alt_id": "", "portrait_object_id": "923955", "status_id": "3"}, {"age_days": "235", "age_years": "28", "alpha_name": "DHONI,MS", "batting_hand": "right-hand batsman", "batting_style": "rhb", "batting_style_long": "right-hand bat", "bowling_hand": "right-arm bowler", "bowling_pacespin": "pace bowler", "bowling_style": "rm", "bowling_style_long": "right-arm medium ", "captain": "1", "card_long": "MS Dhoni", "card_qualifier": "", "card_short": "Dhoni", "dob": "1981-07-07", "keeper": "1", "known_as": "MS Dhoni", "mobile_name": "Dhoni", "object_id": "28081", "player_id": "7593", "player_primary_role": "wicketkeeper batsman", "player_style_id": "7", "player_type": "1", "player_type_name": "player", "popular_name": "Dhoni", "portrait_alt_id": "20", "portrait_object_id": "1099927", "status_id": "3"}, {"age_days": "92", "age_years": "23", "alpha_name": "RAINA,SK", "batting_hand": "left-hand batsman", "batting_style": "lhb", "batting_style_long": "left-hand bat", "bowling_hand": "right-arm bowler", "bowling_pacespin": "spin bowler", "bowling_style": "ob", "bowling_style_long": "right-arm offbreak ", "captain": "0", "card_long": "SK Raina", "card_qualifier": "", "card_short": "Raina", "dob": "1986-11-27", "keeper": "0", "known_as": "Suresh Raina", "mobile_name": "Raina", "object_id": "33335", "player_id": "15716", "player_primary_role": "middle-order batsman", "player_style_id": "3", "player_type": "1", "player_type_name": "player", "popular_name": "Raina", "portrait_alt_id": "1", "portrait_object_id": "817337", "status_id": "3"}, {"age_days": "102", "age_years": "27", "alpha_name": "PATHAN,YK", "batting_hand": "right-hand batsman", "batting_style": "rhb", "batting_style_long": "right-hand bat", "bowling_hand": "right-arm bowler", "bowling_pacespin": "spin bowler", "bowling_style": "ob", "bowling_style_long": "right-arm offbreak ", "captain": "0", "card_long": "YK Pathan", "card_qualifier": "", "card_short": "Pathan", "dob": "1982-11-17", "keeper": "0", "known_as": "Yusuf Pathan", "mobile_name": "Pathan", "object_id": "32498", "player_id": "15473", "player_primary_role": "allrounder", "player_style_id": "5", "player_type": "1", "player_type_name": "player", "popular_name": "Yusuf", "portrait_alt_id": "1", "portrait_object_id": "817505", "status_id": "3"}, {"age_days": "83", "age_years": "21", "alpha_name": "JADEJA,RA", "batting_hand": "left-hand batsman", "batting_style": "lhb", "batting_style_long": "left-hand bat", "bowling_hand": "left-arm bowler", "bowling_pacespin": "spin bowler", "bowling_style": "sla", "bowling_style_long": "slow left-arm orthodox ", "captain": "0", "card_long": "RA Jadeja", "card_qualifier": "", "card_short": "Jadeja", "dob": "1988-12-06", "keeper": "0", "known_as": "Ravindra Jadeja", "mobile_name": "Jadeja", "object_id": "234675", "player_id": "49247", "player_primary_role": "allrounder", "player_style_id": "5", "player_type": "1", "player_type_name": "player", "popular_name": "Jadeja", "portrait_alt_id": "21", "portrait_object_id": "1099918", "status_id": "3"}, {"age_days": "21", "age_years": "27", "alpha_name": "SREESANTH,S", "batting_hand": "right-hand batsman", "batting_style": "rhb", "batting_style_long": "right-hand bat", "bowling_hand": "right-arm bowler", "bowling_pacespin": "pace bowler", "bowling_style": "rfm", "bowling_style_long": "right-arm fast-medium ", "captain": "0", "card_long": "S Sreesanth", "card_qualifier": "", "card_short": "Sreesanth", "dob": "1983-02-06", "keeper": "0", "known_as": "Sreesanth", "mobile_name": "Sreesanth", "object_id": "34274", "player_id": "12020", "player_primary_role": "bowler", "player_style_id": "4", "player_type": "1", "player_type_name": "player", "popular_name": "", "portrait_alt_id": "1", "portrait_object_id": "501526", "status_id": "3"}, {"age_days": "125", "age_years": "20", "alpha_name": "MITHUN,A", "batting_hand": "right-hand batsman", "batting_style": "rhb", "batting_style_long": "right-hand bat", "bowling_hand": "right-arm bowler", "bowling_pacespin": "pace bowler", "bowling_style": "rm", "bowling_style_long": "right-arm medium ", "captain": "0", "card_long": "A Mithun", "card_qualifier": "", "card_short": "Mithun", "dob": "1989-10-25", "keeper": "0", "known_as": "Abhimanyu Mithun", "mobile_name": "Mithun", "object_id": "310958", "player_id": "53314", "player_primary_role": "bowler", "player_style_id": "4", "player_type": "1", "player_type_name": "player", "popular_name": "Mithun", "portrait_alt_id": "", "portrait_object_id": "802335", "status_id": "3"}, {"age_days": "163", "age_years": "22", "alpha_name": "TYAGI,S", "batting_hand": "right-hand batsman", "batting_style": "rhb", "batting_style_long": "right-hand bat", "bowling_hand": "right-arm bowler", "bowling_pacespin": "pace bowler", "bowling_style": "rm", "bowling_style_long": "right-arm medium ", "captain": "0", "card_long": "S Tyagi", "card_qualifier": "", "card_short": "Tyagi", "dob": "1987-09-17", "keeper": "0", "known_as": "Sudeep Tyagi", "mobile_name": "Tyagi", "object_id": "317784", "player_id": "53581", "player_primary_role": "bowler", "player_style_id": "4", "player_type": "1", "player_type_name": "player", "popular_name": "Tyagi", "portrait_alt_id": "1", "portrait_object_id": "437547", "status_id": "3"}], "roster_list": ["KD Karthik", "M Vijay", "V Kohli", "RG Sharma", "MS Dhoni", "SK Raina", "YK Pathan", "RA Jadeja", "S Sreesanth", "A Mithun", "S Tyagi"]}, "team_2": {"team_name": "South Africa", "athlete_info_list": [{"age_days": "319", "age_years": "32", "alpha_name": "BOSMAN,LE", "batting_hand": "right-hand batsman", "batting_style": "rhb", "batting_style_long": "right-hand bat", "bowling_hand": "right-arm bowler", "bowling_pacespin": "pace bowler", "bowling_style": "rm", "bowling_style_long": "right-arm medium ", "captain": "0", "card_long": "LE Bosman", "card_qualifier": "", "card_short": "Bosman", "dob": "1977-04-14", "keeper": "0", "known_as": "Loots Bosman", "mobile_name": "Bosman", "object_id": "44098", "player_id": "7538", "player_primary_role": null, "player_style_id": null, "player_type": "1", "player_type_name": "player", "popular_name": "Bosman", "portrait_alt_id": "1", "portrait_object_id": "512773", "status_id": "3"}, {"age_days": "333", "age_years": "26", "alpha_name": "AMLA,HM", "batting_hand": "right-hand batsman", "batting_style": "rhb", "batting_style_long": "right-hand bat", "bowling_hand": "right-arm bowler", "bowling_pacespin": "mixture/unknown", "bowling_style": "rm/ob", "bowling_style_long": "right-arm medium /right-arm offbreak ", "captain": "0", "card_long": "HM Amla", "card_qualifier": "", "card_short": "Amla", "dob": "1983-03-31", "keeper": "0", "known_as": "Hashim Amla", "mobile_name": "Amla", "object_id": "43906", "player_id": "9952", "player_primary_role": "top-order batsman", "player_style_id": "2", "player_type": "1", "player_type_name": "player", "popular_name": "Amla", "portrait_alt_id": "1", "portrait_object_id": "1100134", "status_id": "3"}, {"age_days": "134", "age_years": "34", "alpha_name": "KALLIS,JH", "batting_hand": "right-hand batsman", "batting_style": "rhb", "batting_style_long": "right-hand bat", "bowling_hand": "right-arm bowler", "bowling_pacespin": "pace bowler", "bowling_style": "rfm", "bowling_style_long": "right-arm fast-medium ", "captain": "1", "card_long": "JH Kallis", "card_qualifier": "", "card_short": "Kallis", "dob": "1975-10-16", "keeper": "0", "known_as": "Jacques Kallis", "mobile_name": "Kallis", "object_id": "45789", "player_id": "2232", "player_primary_role": "allrounder", "player_style_id": "5", "player_type": "1", "player_type_name": "player", "popular_name": "Kallis", "portrait_alt_id": "1", "portrait_object_id": "818335", "status_id": "3"}, {"age_days": "10", "age_years": "26", "alpha_name": "DEVILLIERS,AB", "batting_hand": "right-hand batsman", "batting_style": "rhb", "batting_style_long": "right-hand bat", "bowling_hand": "right-arm bowler", "bowling_pacespin": "pace bowler", "bowling_style": "rm", "bowling_style_long": "right-arm medium ", "captain": "0", "card_long": "AB de Villiers", "card_qualifier": "", "card_short": "de Villiers", "dob": "1984-02-17", "keeper": "0", "known_as": "AB de Villiers", "mobile_name": "AB", "object_id": "44936", "player_id": "46533", "player_primary_role": "wicketkeeper batsman", "player_style_id": "7", "player_type": "1", "player_type_name": "player", "popular_name": "AB", "portrait_alt_id": "1", "portrait_object_id": "1100133", "status_id": "3"}, {"age_days": "4", "age_years": "36", "alpha_name": "GIBBS,HH", "batting_hand": "right-hand batsman", "batting_style": "rhb", "batting_style_long": "right-hand bat", "bowling_hand": "right-arm bowler", "bowling_pacespin": "mixture/unknown", "bowling_style": "rab", "bowling_style_long": "right-arm bowler ", "captain": "0", "card_long": "HH Gibbs", "card_qualifier": "", "card_short": "Gibbs", "dob": "1974-02-23", "keeper": "0", "known_as": "Herschelle Gibbs", "mobile_name": "Gibbs", "object_id": "45224", "player_id": "2347", "player_primary_role": null, "player_style_id": null, "player_type": "1", "player_type_name": "player", "popular_name": "Gibbs", "portrait_alt_id": "1", "portrait_object_id": "567985", "status_id": "3"}, {"age_days": "86", "age_years": "33", "alpha_name": "BOUCHER,MV", "batting_hand": "right-hand batsman", "batting_style": "rhb", "batting_style_long": "right-hand bat", "bowling_hand": "right-arm bowler", "bowling_pacespin": "pace bowler", "bowling_style": "rm", "bowling_style_long": "right-arm medium ", "captain": "0", "card_long": "MV Boucher", "card_qualifier": "", "card_short": "Boucher", "dob": "1976-12-03", "keeper": "1", "known_as": "Mark Boucher", "mobile_name": "Boucher", "object_id": "44111", "player_id": "3947", "player_primary_role": "wicketkeeper batsman", "player_style_id": "7", "player_type": "1", "player_type_name": "player", "popular_name": "Boucher", "portrait_alt_id": "1", "portrait_object_id": "531383", "status_id": "3"}, {"age_days": "301", "age_years": "27", "alpha_name": "BOTHA,J", "batting_hand": "right-hand batsman", "batting_style": "rhb", "batting_style_long": "right-hand bat", "bowling_hand": "right-arm bowler", "bowling_pacespin": "spin bowler", "bowling_style": "ob", "bowling_style_long": "right-arm offbreak ", "captain": "0", "card_long": "J Botha", "card_qualifier": "", "card_short": "Botha", "dob": "1982-05-02", "keeper": "0", "known_as": "Johan Botha", "mobile_name": "Botha", "object_id": "44149", "player_id": "10401", "player_primary_role": "allrounder", "player_style_id": "5", "player_type": "1", "player_type_name": "player", "popular_name": "Botha", "portrait_alt_id": "1", "portrait_object_id": "818353", "status_id": "3"}, {"age_days": "58", "age_years": "25", "alpha_name": "VANDERMERWE,RE", "batting_hand": "right-hand batsman", "batting_style": "rhb", "batting_style_long": "right-hand bat", "bowling_hand": "left-arm bowler", "bowling_pacespin": "spin bowler", "bowling_style": "sla", "bowling_style_long": "slow left-arm orthodox ", "captain": "0", "card_long": "RE van der Merwe", "card_qualifier": "", "card_short": "van der Merwe", "dob": "1984-12-31", "keeper": "0", "known_as": "Roelof van der Merwe", "mobile_name": "Roelof", "object_id": "47850", "player_id": "47391", "player_primary_role": "allrounder", "player_style_id": "5", "player_type": "1", "player_type_name": "player", "popular_name": "Roelof", "portrait_alt_id": "1", "portrait_object_id": "897489", "status_id": "3"}, {"age_days": "245", "age_years": "26", "alpha_name": "STEYN,DW", "batting_hand": "right-hand batsman", "batting_style": "rhb", "batting_style_long": "right-hand bat", "bowling_hand": "right-arm bowler", "bowling_pacespin": "pace bowler", "bowling_style": "rf", "bowling_style_long": "right-arm fast ", "captain": "0", "card_long": "DW Steyn", "card_qualifier": "", "card_short": "Steyn", "dob": "1983-06-27", "keeper": "0", "known_as": "Dale Steyn", "mobile_name": "Steyn", "object_id": "47492", "player_id": "47154", "player_primary_role": "bowler", "player_style_id": "4", "player_type": "1", "player_type_name": "player", "popular_name": "Steyn", "portrait_alt_id": "", "portrait_object_id": "1185195", "status_id": "3"}, {"age_days": "144", "age_years": "25", "alpha_name": "MORKEL,M", "batting_hand": "left-hand batsman", "batting_style": "lhb", "batting_style_long": "left-hand bat", "bowling_hand": "right-arm bowler", "bowling_pacespin": "pace bowler", "bowling_style": "rf", "bowling_style_long": "right-arm fast ", "captain": "0", "card_long": "M Morkel", "card_qualifier": "", "card_short": "Morkel", "dob": "1984-10-06", "keeper": "0", "known_as": "Morne Morkel", "mobile_name": "Morkel", "object_id": "46538", "player_id": "47289", "player_primary_role": "bowler", "player_style_id": "4", "player_type": "1", "player_type_name": "player", "popular_name": "Morne", "portrait_alt_id": "1", "portrait_object_id": "1100154", "status_id": "3"}, {"age_days": "357", "age_years": "25", "alpha_name": "TSOTSOBE,LL", "batting_hand": "right-hand batsman", "batting_style": "rhb", "batting_style_long": "right-hand bat", "bowling_hand": "left-arm bowler", "bowling_pacespin": "pace bowler", "bowling_style": "lfm", "bowling_style_long": "left-arm fast-medium ", "captain": "0", "card_long": "LL Tsotsobe", "card_qualifier": "", "card_short": "Tsotsobe", "dob": "1984-03-07", "keeper": "0", "known_as": "Lonwabo Tsotsobe", "mobile_name": "Tsotsobe", "object_id": "47666", "player_id": "48182", "player_primary_role": "bowler", "player_style_id": "4", "player_type": "1", "player_type_name": "player", "popular_name": "Tsotsobe", "portrait_alt_id": "1", "portrait_object_id": "818393", "status_id": "3"}], "roster_list": ["LE Bosman", "HM Amla", "JH Kallis", "AB de Villiers", "HH Gibbs", "MV Boucher", "J Botha", "RE van der Merwe", "DW Steyn", "M Morkel", "LL Tsotsobe"]}}