{"team_1": {"team_name": "England", "athlete_info_list": [{"age_days": "50", "age_years": "27", "alpha_name": "COOK,AN", "batting_hand": "left-hand batsman", "batting_style": "lhb", "batting_style_long": "left-hand bat", "bowling_hand": "right-arm bowler", "bowling_pacespin": "mixture/unknown", "bowling_style": "rs", "bowling_style_long": "right-arm slow ", "captain": "1", "card_long": "AN Cook", "card_qualifier": "", "card_short": "Cook", "dob": "1984-12-25", "keeper": "0", "known_as": "Sir Alastair Cook", "mobile_name": "Cook", "object_id": "11728", "player_id": "45788", "player_primary_role": "opening batsman", "player_style_id": "1", "player_type": "1", "player_type_name": "player", "popular_name": "Cook", "portrait_alt_id": "", "portrait_object_id": "1015841", "status_id": "3"}, {"age_days": "231", "age_years": "31", "alpha_name": "PIETERSEN,KP", "batting_hand": "right-hand batsman", "batting_style": "rhb", "batting_style_long": "right-hand bat", "bowling_hand": "right-arm bowler", "bowling_pacespin": "spin bowler", "bowling_style": "ob", "bowling_style_long": "right-arm offbreak ", "captain": "0", "card_long": "KP Pietersen", "card_qualifier": "", "card_short": "Pietersen", "dob": "1980-06-27", "keeper": "0", "known_as": "Kevin Pietersen", "mobile_name": "Pietersen", "object_id": "19296", "player_id": "8107", "player_primary_role": "top-order batsman", "player_style_id": "2", "player_type": "1", "player_type_name": "player", "popular_name": "KP", "portrait_alt_id": "1", "portrait_object_id": "565726", "status_id": "3"}, {"age_days": "297", "age_years": "30", "alpha_name": "TROTT,IJL", "batting_hand": "right-hand batsman", "batting_style": "rhb", "batting_style_long": "right-hand bat", "bowling_hand": "right-arm bowler", "bowling_pacespin": "pace bowler", "bowling_style": "rm", "bowling_style_long": "right-arm medium ", "captain": "0", "card_long": "IJL Trott", "card_qualifier": "", "card_short": "Trott", "dob": "1981-04-22", "keeper": "0", "known_as": "Jonathan Trott", "mobile_name": "Trott", "object_id": "47623", "player_id": "10407", "player_primary_role": "top-order batsman", "player_style_id": "2", "player_type": "1", "player_type_name": "player", "popular_name": "Trott", "portrait_alt_id": "1", "portrait_object_id": "565714", "status_id": "3"}, {"age_days": "285", "age_years": "26", "alpha_name": "BOPARA,RS", "batting_hand": "right-hand batsman", "batting_style": "rhb", "batting_style_long": "right-hand bat", "bowling_hand": "right-arm bowler", "bowling_pacespin": "pace bowler", "bowling_style": "rm", "bowling_style_long": "right-arm medium ", "captain": "0", "card_long": "RS Bopara", "card_qualifier": "", "card_short": "Bopara", "dob": "1985-05-04", "keeper": "0", "known_as": "Ravi Bopara", "mobile_name": "Bopara", "object_id": "10582", "player_id": "44691", "player_primary_role": "batting allrounder", "player_style_id": "10", "player_type": "1", "player_type_name": "player", "popular_name": "Bopara", "portrait_alt_id": "1", "portrait_object_id": "818131", "status_id": "3"}, {"age_days": "156", "age_years": "25", "alpha_name": "MORGAN,EJG", "batting_hand": "left-hand batsman", "batting_style": "lhb", "batting_style_long": "left-hand bat", "bowling_hand": "right-arm bowler", "bowling_pacespin": "pace bowler", "bowling_style": "rm", "bowling_style_long": "right-arm medium ", "captain": "0", "card_long": "EJG Morgan", "card_qualifier": "", "card_short": "Morgan", "dob": "1986-09-10", "keeper": "0", "known_as": "Eoin Morgan", "mobile_name": "Morgan", "object_id": "24598", "player_id": "47055", "player_primary_role": "middle-order batsman", "player_style_id": "3", "player_type": "1", "player_type_name": "player", "popular_name": "Morgan", "portrait_alt_id": "1", "portrait_object_id": "1185166", "status_id": "3"}, {"age_days": "77", "age_years": "24", "alpha_name": "KIESWETTER,C", "batting_hand": "right-hand batsman", "batting_style": "rhb", "batting_style_long": "right-hand bat", "bowling_hand": "right-arm bowler", "bowling_pacespin": "spin bowler", "bowling_style": "ob", "bowling_style_long": "right-arm offbreak ", "captain": "0", "card_long": "C Kieswetter", "card_qualifier": "", "card_short": "Kieswetter", "dob": "1987-11-28", "keeper": "1", "known_as": "Craig Kieswetter", "mobile_name": "Kieswetter", "object_id": "230855", "player_id": "49047", "player_primary_role": "opening batsman", "player_style_id": "1", "player_type": "1", "player_type_name": "player", "popular_name": "CK", "portrait_alt_id": "1", "portrait_object_id": "889977", "status_id": "3"}, {"age_days": "75", "age_years": "27", "alpha_name": "PATEL,SR", "batting_hand": "right-hand batsman", "batting_style": "rhb", "batting_style_long": "right-hand bat", "bowling_hand": "left-arm bowler", "bowling_pacespin": "spin bowler", "bowling_style": "sla", "bowling_style_long": "slow left-arm orthodox ", "captain": "0", "card_long": "SR Patel", "card_qualifier": "", "card_short": "Patel", "dob": "1984-11-30", "keeper": "0", "known_as": "Samit Patel", "mobile_name": "Patel", "object_id": "18632", "player_id": "34736", "player_primary_role": "allrounder", "player_style_id": "5", "player_type": "1", "player_type_name": "player", "popular_name": "Samit", "portrait_alt_id": "1", "portrait_object_id": "818121", "status_id": "3"}, {"age_days": "234", "age_years": "25", "alpha_name": "BROAD,SCJ", "batting_hand": "left-hand batsman", "batting_style": "lhb", "batting_style_long": "left-hand bat", "bowling_hand": "right-arm bowler", "bowling_pacespin": "pace bowler", "bowling_style": "rfm", "bowling_style_long": "right-arm fast-medium ", "captain": "0", "card_long": "SCJ Broad", "card_qualifier": "", "card_short": "Broad", "dob": "1986-06-24", "keeper": "0", "known_as": "Stuart Broad", "mobile_name": "Broad", "object_id": "10617", "player_id": "48440", "player_primary_role": "bowler", "player_style_id": "4", "player_type": "1", "player_type_name": "player", "popular_name": "Broad", "portrait_alt_id": "1", "portrait_object_id": "818153", "status_id": "3"}, {"age_days": "326", "age_years": "32", "alpha_name": "SWANN,GP", "batting_hand": "right-hand batsman", "batting_style": "rhb", "batting_style_long": "right-hand bat", "bowling_hand": "right-arm bowler", "bowling_pacespin": "spin bowler", "bowling_style": "ob", "bowling_style_long": "right-arm offbreak ", "captain": "0", "card_long": "GP Swann", "card_qualifier": "", "card_short": "Swann", "dob": "1979-03-24", "keeper": "0", "known_as": "Graeme Swann", "mobile_name": "Swann", "object_id": "20431", "player_id": "7013", "player_primary_role": "bowler", "player_style_id": "4", "player_type": "1", "player_type_name": "player", "popular_name": "Swann", "portrait_alt_id": "1", "portrait_object_id": "565723", "status_id": "3"}, {"age_days": "198", "age_years": "29", "alpha_name": "ANDERSON,JM", "batting_hand": "left-hand batsman", "batting_style": "lhb", "batting_style_long": "left-hand bat", "bowling_hand": "right-arm bowler", "bowling_pacespin": "pace bowler", "bowling_style": "rfm", "bowling_style_long": "right-arm fast-medium ", "captain": "0", "card_long": "JM Anderson", "card_qualifier": "", "card_short": "Anderson", "dob": "1982-07-30", "keeper": "0", "known_as": "James Anderson", "mobile_name": "Anderson", "object_id": "8608", "player_id": "10829", "player_primary_role": "bowler", "player_style_id": "4", "player_type": "1", "player_type_name": "player", "popular_name": "Anderson", "portrait_alt_id": "", "portrait_object_id": "1015875", "status_id": "3"}, {"age_days": "315", "age_years": "22", "alpha_name": "FINN,ST", "batting_hand": "right-hand batsman", "batting_style": "rhb", "batting_style_long": "right-hand bat", "bowling_hand": "right-arm bowler", "bowling_pacespin": "pace bowler", "bowling_style": "rfm", "bowling_style_long": "right-arm fast-medium ", "captain": "0", "card_long": "ST Finn", "card_qualifier": "", "card_short": "Finn", "dob": "1989-04-04", "keeper": "0", "known_as": "Steven Finn", "mobile_name": "Finn", "object_id": "210283", "player_id": "48529", "player_primary_role": "bowler", "player_style_id": "4", "player_type": "1", "player_type_name": "player", "popular_name": "Finn", "portrait_alt_id": "", "portrait_object_id": "1015869", "status_id": "3"}], "roster_list": ["AN Cook", "KP Pietersen", "IJL Trott", "RS Bopara", "EJG Morgan", "C Kieswetter", "SR Patel", "SCJ Broad", "GP Swann", "JM Anderson", "ST Finn"]}, "team_2": {"team_name": "Pakistan", "athlete_info_list": [{"age_days": "119", "age_years": "31", "alpha_name": "MOHAMMAD_HAFEEZ", "batting_hand": "right-hand batsman", "batting_style": "rhb", "batting_style_long": "right-hand bat", "bowling_hand": "right-arm bowler", "bowling_pacespin": "spin bowler", "bowling_style": "ob", "bowling_style_long": "right-arm offbreak ", "captain": "0", "card_long": "Mohammad Hafeez", "card_qualifier": "", "card_short": "Mohammad Hafeez", "dob": "1980-10-17", "keeper": "0", "known_as": "Mohammad Hafeez", "mobile_name": "Hafeez", "object_id": "41434", "player_id": "19647", "player_primary_role": "allrounder", "player_style_id": "5", "player_type": "1", "player_type_name": "player", "popular_name": "Hafeez", "portrait_alt_id": "1", "portrait_object_id": "1099686", "status_id": "3"}, {"age_days": "269", "age_years": "29", "alpha_name": "IMRAN_FARHAT", "batting_hand": "left-hand batsman", "batting_style": "lhb", "batting_style_long": "left-hand bat", "bowling_hand": "right-arm bowler", "bowling_pacespin": "spin bowler", "bowling_style": "lb", "bowling_style_long": "legbreak ", "captain": "0", "card_long": "Imran Farhat", "card_qualifier": "", "card_short": "Imran Farhat", "dob": "1982-05-20", "keeper": "0", "known_as": "Imran Farhat", "mobile_name": "Farhat", "object_id": "40582", "player_id": "10392", "player_primary_role": null, "player_style_id": null, "player_type": "1", "player_type_name": "player", "popular_name": "Farhat", "portrait_alt_id": "1", "portrait_object_id": "818275", "status_id": "3"}, {"age_days": "16", "age_years": "26", "alpha_name": "ASAD_SHAFIQ", "batting_hand": "right-hand batsman", "batting_style": "rhb", "batting_style_long": "right-hand bat", "bowling_hand": "right-arm bowler", "bowling_pacespin": "spin bowler", "bowling_style": "ob", "bowling_style_long": "right-arm offbreak ", "captain": "0", "card_long": "Asad Shafiq", "card_qualifier": "", "card_short": "Asad Shafiq", "dob": "1986-01-28", "keeper": "0", "known_as": "Asad Shafiq", "mobile_name": "Shafiq", "object_id": "316397", "player_id": "53493", "player_primary_role": "middle-order batsman", "player_style_id": "3", "player_type": "1", "player_type_name": "player", "popular_name": "Shafiq", "portrait_alt_id": "1", "portrait_object_id": "818317", "status_id": "3"}, {"age_days": "76", "age_years": "34", "alpha_name": "YOUNIS_KHAN", "batting_hand": "right-hand batsman", "batting_style": "rhb", "batting_style_long": "right-hand bat", "bowling_hand": "right-arm bowler", "bowling_pacespin": "mixture/unknown", "bowling_style": "rm/lb", "bowling_style_long": "right-arm medium /legbreak ", "captain": "0", "card_long": "Younis Khan", "card_qualifier": "", "card_short": "Younis Khan", "dob": "1977-11-29", "keeper": "0", "known_as": "Younis Khan", "mobile_name": "Younis", "object_id": "43652", "player_id": "10439", "player_primary_role": "middle-order batsman", "player_style_id": "3", "player_type": "1", "player_type_name": "player", "popular_name": "Younis", "portrait_alt_id": "1", "portrait_object_id": "1072171", "status_id": "3"}, {"age_days": "261", "age_years": "37", "alpha_name": "MISBAHULHAQ", "batting_hand": "right-hand batsman", "batting_style": "rhb", "batting_style_long": "right-hand bat", "bowling_hand": "right-arm bowler", "bowling_pacespin": "spin bowler", "bowling_style": "lb", "bowling_style_long": "legbreak ", "captain": "1", "card_long": "Misbah-ul-Haq", "card_qualifier": "", "card_short": "Misbah-ul-Haq", "dob": "1974-05-28", "keeper": "0", "known_as": "Misbah-ul-Haq", "mobile_name": "Misbah", "object_id": "41378", "player_id": "19596", "player_primary_role": "middle-order batsman", "player_style_id": "3", "player_type": "1", "player_type_name": "player", "popular_name": "Misbah", "portrait_alt_id": "1", "portrait_object_id": "1072174", "status_id": "3"}, {"age_days": "263", "age_years": "21", "alpha_name": "UMAR_AKMAL", "batting_hand": "right-hand batsman", "batting_style": "rhb", "batting_style_long": "right-hand bat", "bowling_hand": "unknown arm", "bowling_pacespin": "mixture/unknown", "bowling_style": null, "bowling_style_long": null, "captain": "0", "card_long": "Umar Akmal", "card_qualifier": "", "card_short": "Umar Akmal", "dob": "1990-05-26", "keeper": "1", "known_as": "Umar Akmal", "mobile_name": "Umar Akmal", "object_id": "317273", "player_id": "53546", "player_primary_role": "middle-order batsman", "player_style_id": "3", "player_type": "1", "player_type_name": "player", "popular_name": "Akmal", "portrait_alt_id": "", "portrait_object_id": "983035", "status_id": "3"}, {"age_days": "12", "age_years": "30", "alpha_name": "SHOAIB_MALIK", "batting_hand": "right-hand batsman", "batting_style": "rhb", "batting_style_long": "right-hand bat", "bowling_hand": "right-arm bowler", "bowling_pacespin": "spin bowler", "bowling_style": "ob", "bowling_style_long": "right-arm offbreak ", "captain": "0", "card_long": "Shoaib Malik", "card_qualifier": "", "card_short": "Shoaib Malik", "dob": "1982-02-01", "keeper": "0", "known_as": "Shoaib Malik", "mobile_name": "Malik", "object_id": "42657", "player_id": "8270", "player_primary_role": "allrounder", "player_style_id": "5", "player_type": "1", "player_type_name": "player", "popular_name": "Malik", "portrait_alt_id": "1", "portrait_object_id": "1099697", "status_id": "3"}, {"age_days": "349", "age_years": "31", "alpha_name": "SHAHID_AFRIDI", "batting_hand": "right-hand batsman", "batting_style": "rhb", "batting_style_long": "right-hand bat", "bowling_hand": "right-arm bowler", "bowling_pacespin": "spin bowler", "bowling_style": "lbg", "bowling_style_long": "legbreak googly ", "captain": "0", "card_long": "Shahid Afridi", "card_qualifier": "", "card_short": "Shahid Afridi", "dob": "1980-03-01", "keeper": "0", "known_as": "Shahid Afridi", "mobile_name": "Afridi", "object_id": "42639", "player_id": "4169", "player_primary_role": "allrounder", "player_style_id": "5", "player_type": "1", "player_type_name": "player", "popular_name": "Afridi", "portrait_alt_id": "1", "portrait_object_id": "818259", "status_id": "3"}, {"age_days": "305", "age_years": "27", "alpha_name": "UMAR_GUL", "batting_hand": "right-hand batsman", "batting_style": "rhb", "batting_style_long": "right-hand bat", "bowling_hand": "right-arm bowler", "bowling_pacespin": "pace bowler", "bowling_style": "rfm", "bowling_style_long": "right-arm fast-medium ", "captain": "0", "card_long": "Umar Gul", "card_qualifier": "", "card_short": "Umar Gul", "dob": "1984-04-14", "keeper": "0", "known_as": "Umar Gul", "mobile_name": "Umar Gul", "object_id": "43524", "player_id": "44908", "player_primary_role": "bowler", "player_style_id": "4", "player_type": "1", "player_type_name": "player", "popular_name": "Gul", "portrait_alt_id": "1", "portrait_object_id": "818305", "status_id": "3"}, {"age_days": "122", "age_years": "34", "alpha_name": "SAEED_AJMAL", "batting_hand": "right-hand batsman", "batting_style": "rhb", "batting_style_long": "right-hand bat", "bowling_hand": "right-arm bowler", "bowling_pacespin": "spin bowler", "bowling_style": "ob", "bowling_style_long": "right-arm offbreak ", "captain": "0", "card_long": "Saeed Ajmal", "card_qualifier": "", "card_short": "Saeed Ajmal", "dob": "1977-10-14", "keeper": "0", "known_as": "Saeed Ajmal", "mobile_name": "Ajmal", "object_id": "42699", "player_id": "19930", "player_primary_role": "bowler", "player_style_id": "4", "player_type": "1", "player_type_name": "player", "popular_name": "Ajmal", "portrait_alt_id": "1", "portrait_object_id": "818301", "status_id": "3"}, {"age_days": "230", "age_years": "26", "alpha_name": "WAHAB_RIAZ", "batting_hand": "right-hand batsman", "batting_style": "rhb", "batting_style_long": "right-hand bat", "bowling_hand": "left-arm bowler", "bowling_pacespin": "pace bowler", "bowling_style": "lf", "bowling_style_long": "left-arm fast ", "captain": "0", "card_long": "Wahab Riaz", "card_qualifier": "", "card_short": "Wahab Riaz", "dob": "1985-06-28", "keeper": "0", "known_as": "Wahab Riaz", "mobile_name": "Wahab Riaz", "object_id": "43590", "player_id": "24723", "player_primary_role": "bowler", "player_style_id": "4", "player_type": "1", "player_type_name": "player", "popular_name": "Wahab", "portrait_alt_id": "1", "portrait_object_id": "1099704", "status_id": "3"}], "roster_list": ["Mohammad Hafeez", "Imran Farhat", "Asad Shafiq", "Younis Khan", "Misbah-ul-Haq", "Umar Akmal", "Shoaib Malik", "Shahid Afridi", "Umar Gul", "Saeed Ajmal", "Wahab Riaz"]}}