{"team_1": {"team_name": "West Indies", "athlete_info_list": [{"age_days": "63", "age_years": "26", "alpha_name": "HOPE,SD", "batting_hand": "right-hand batsman", "batting_style": "rhb", "batting_style_long": "right-hand bat", "bowling_hand": "unknown arm", "bowling_pacespin": "mixture/unknown", "bowling_style": null, "bowling_style_long": null, "captain": "0", "card_long": "SD Hope", "card_qualifier": "", "card_short": "Hope", "dob": "1993-11-10", "keeper": "1", "known_as": "Shai Hope", "mobile_name": "Hope", "object_id": "581379", "player_id": "68405", "player_primary_role": "wicketkeeper batsman", "player_style_id": "7", "player_type": "1", "player_type_name": "player", "popular_name": "Hope", "portrait_alt_id": "1", "portrait_object_id": "883993", "status_id": "3"}, {"age_days": "16", "age_years": "28", "alpha_name": "LEWIS,E", "batting_hand": "left-hand batsman", "batting_style": "lhb", "batting_style_long": "left-hand bat", "bowling_hand": "unknown arm", "bowling_pacespin": "mixture/unknown", "bowling_style": null, "bowling_style_long": null, "captain": "0", "card_long": "E Lewis", "card_qualifier": "", "card_short": "Lewis", "dob": "1991-12-27", "keeper": "0", "known_as": "Evin Lewis", "mobile_name": "Lewis", "object_id": "431901", "player_id": "61413", "player_primary_role": "opening batsman", "player_style_id": "1", "player_type": "1", "player_type_name": "player", "popular_name": "Lewis", "portrait_alt_id": "", "portrait_object_id": "966389", "status_id": "3"}, {"age_days": "295", "age_years": "26", "alpha_name": "AMBRIS,SW", "batting_hand": "right-hand batsman", "batting_style": "rhb", "batting_style_long": "right-hand bat", "bowling_hand": "unknown arm", "bowling_pacespin": "mixture/unknown", "bowling_style": null, "bowling_style_long": null, "captain": "0", "card_long": "SW Ambris", "card_qualifier": "", "card_short": "Ambris", "dob": "1993-03-23", "keeper": "0", "known_as": "Sunil Ambris", "mobile_name": "Ambris", "object_id": "348054", "player_id": "56830", "player_primary_role": "opening batsman", "player_style_id": "1", "player_type": "1", "player_type_name": "player", "popular_name": "Ambris", "portrait_alt_id": "1", "portrait_object_id": "530817", "status_id": "3"}, {"age_days": "27", "age_years": "25", "alpha_name": "KING,BA", "batting_hand": "right-hand batsman", "batting_style": "rhb", "batting_style_long": "right-hand bat", "bowling_hand": "unknown arm", "bowling_pacespin": "mixture/unknown", "bowling_style": null, "bowling_style_long": null, "captain": "0", "card_long": "BA King", "card_qualifier": "", "card_short": "King", "dob": "1994-12-16", "keeper": "0", "known_as": "Brandon King", "mobile_name": "King", "object_id": "670035", "player_id": "72399", "player_primary_role": "top-order batsman", "player_style_id": "2", "player_type": "1", "player_type_name": "player", "popular_name": "King", "portrait_alt_id": "", "portrait_object_id": "966419", "status_id": "3"}, {"age_days": "102", "age_years": "24", "alpha_name": "POORAN,N", "batting_hand": "left-hand batsman", "batting_style": "lhb", "batting_style_long": "left-hand bat", "bowling_hand": "unknown arm", "bowling_pacespin": "mixture/unknown", "bowling_style": null, "bowling_style_long": null, "captain": "0", "card_long": "N Pooran", "card_qualifier": "", "card_short": "Pooran", "dob": "1995-10-02", "keeper": "0", "known_as": "Nicholas Pooran", "mobile_name": "Pooran", "object_id": "604302", "player_id": "70405", "player_primary_role": "wicketkeeper batsman", "player_style_id": "7", "player_type": "1", "player_type_name": "player", "popular_name": "Pooran", "portrait_alt_id": "1", "portrait_object_id": "679735", "status_id": "3"}, {"age_days": "47", "age_years": "25", "alpha_name": "SHEPHERD,R", "batting_hand": "right-hand batsman", "batting_style": "rhb", "batting_style_long": "right-hand bat", "bowling_hand": "right-arm bowler", "bowling_pacespin": "pace bowler", "bowling_style": "rmf", "bowling_style_long": "right-arm medium-fast ", "captain": "0", "card_long": "R Shepherd", "card_qualifier": "", "card_short": "Shepherd", "dob": "1994-11-26", "keeper": "0", "known_as": "Romario Shepherd", "mobile_name": "Shepherd", "object_id": "677077", "player_id": "72505", "player_primary_role": "bowler", "player_style_id": "4", "player_type": "1", "player_type_name": "player", "popular_name": "Shepherd", "portrait_alt_id": "", "portrait_object_id": "0", "status_id": "3"}, {"age_days": "296", "age_years": "27", "alpha_name": "CHASE,RL", "batting_hand": "right-hand batsman", "batting_style": "rhb", "batting_style_long": "right-hand bat", "bowling_hand": "right-arm bowler", "bowling_pacespin": "spin bowler", "bowling_style": "ob", "bowling_style_long": "right-arm offbreak ", "captain": "0", "card_long": "RL Chase", "card_qualifier": "", "card_short": "Chase", "dob": "1992-03-22", "keeper": "0", "known_as": "Roston Chase", "mobile_name": "Chase", "object_id": "391832", "player_id": "59349", "player_primary_role": "allrounder", "player_style_id": "5", "player_type": "1", "player_type_name": "player", "popular_name": "Chase", "portrait_alt_id": "", "portrait_object_id": "966447", "status_id": "3"}, {"age_days": "245", "age_years": "32", "alpha_name": "POLLARD,KA", "batting_hand": "right-hand batsman", "batting_style": "rhb", "batting_style_long": "right-hand bat", "bowling_hand": "right-arm bowler", "bowling_pacespin": "pace bowler", "bowling_style": "rm", "bowling_style_long": "right-arm medium ", "captain": "1", "card_long": "KA Pollard", "card_qualifier": "", "card_short": "Pollard", "dob": "1987-05-12", "keeper": "0", "known_as": "Kieron Pollard", "mobile_name": "Pollard", "object_id": "230559", "player_id": "49040", "player_primary_role": "allrounder", "player_style_id": "5", "player_type": "1", "player_type_name": "player", "popular_name": "Pollard", "portrait_alt_id": "1", "portrait_object_id": "818707", "status_id": "3"}, {"age_days": "264", "age_years": "27", "alpha_name": "WALSH,HR", "batting_hand": "left-hand batsman", "batting_style": "lhb", "batting_style_long": "left-hand bat", "bowling_hand": "right-arm bowler", "bowling_pacespin": "spin bowler", "bowling_style": "lbg", "bowling_style_long": "legbreak googly ", "captain": "0", "card_long": "HR Walsh", "card_qualifier": "", "card_short": "Walsh", "dob": "1992-04-23", "keeper": "0", "known_as": "Hayden Walsh", "mobile_name": "Walsh", "object_id": "443263", "player_id": "61941", "player_primary_role": "bowler", "player_style_id": "4", "player_type": "1", "player_type_name": "player", "popular_name": "Walsh", "portrait_alt_id": "1", "portrait_object_id": "1178564", "status_id": "3"}, {"age_days": "53", "age_years": "23", "alpha_name": "JOSEPH,AS", "batting_hand": "right-hand batsman", "batting_style": "rhb", "batting_style_long": "right-hand bat", "bowling_hand": "right-arm bowler", "bowling_pacespin": "pace bowler", "bowling_style": "rfm", "bowling_style_long": "right-arm fast-medium ", "captain": "0", "card_long": "AS Joseph", "card_qualifier": "", "card_short": "Joseph", "dob": "1996-11-20", "keeper": "0", "known_as": "Alzarri Joseph", "mobile_name": "Joseph", "object_id": "670031", "player_id": "72397", "player_primary_role": "bowler", "player_style_id": "4", "player_type": "1", "player_type_name": "player", "popular_name": "Joseph", "portrait_alt_id": "1", "portrait_object_id": "822049", "status_id": "3"}, {"age_days": "328", "age_years": "22", "alpha_name": "THOMAS,O", "batting_hand": "left-hand batsman", "batting_style": "lhb", "batting_style_long": "left-hand bat", "bowling_hand": "right-arm bowler", "bowling_pacespin": "pace bowler", "bowling_style": "rf", "bowling_style_long": "right-arm fast ", "captain": "0", "card_long": "O Thomas", "card_qualifier": "", "card_short": "Thomas", "dob": "1997-02-18", "keeper": "0", "known_as": "Oshane Thomas", "mobile_name": "Thomas", "object_id": "914567", "player_id": "84225", "player_primary_role": "bowler", "player_style_id": "4", "player_type": "1", "player_type_name": "player", "popular_name": "Thomas", "portrait_alt_id": "1", "portrait_object_id": "1030739", "status_id": "3"}], "roster_list": ["SD Hope", "E Lewis", "SW Ambris", "BA King", "N Pooran", "R Shepherd", "RL Chase", "KA Pollard", "HR Walsh", "AS Joseph", "O Thomas"]}, "team_2": {"team_name": "Ireland", "athlete_info_list": [{"age_days": "164", "age_years": "24", "alpha_name": "MCCOLLUM,JA", "batting_hand": "right-hand batsman", "batting_style": "rhb", "batting_style_long": "right-hand bat", "bowling_hand": "right-arm bowler", "bowling_pacespin": "pace bowler", "bowling_style": "rm", "bowling_style_long": "right-arm medium ", "captain": "0", "card_long": "JA McCollum", "card_qualifier": "", "card_short": "McCollum", "dob": "1995-08-01", "keeper": "0", "known_as": "James McCollum", "mobile_name": "McCollum", "object_id": "470917", "player_id": "63179", "player_primary_role": "opening batsman", "player_style_id": "1", "player_type": "1", "player_type_name": "player", "popular_name": "McCollum", "portrait_alt_id": "", "portrait_object_id": "0", "status_id": "3"}, {"age_days": "131", "age_years": "29", "alpha_name": "STIRLING,PR", "batting_hand": "right-hand batsman", "batting_style": "rhb", "batting_style_long": "right-hand bat", "bowling_hand": "right-arm bowler", "bowling_pacespin": "spin bowler", "bowling_style": "ob", "bowling_style_long": "right-arm offbreak ", "captain": "0", "card_long": "PR Stirling", "card_qualifier": "", "card_short": "Stirling", "dob": "1990-09-03", "keeper": "0", "known_as": "Paul Stirling", "mobile_name": "Stirling", "object_id": "303427", "player_id": "52631", "player_primary_role": "allrounder", "player_style_id": "5", "player_type": "1", "player_type_name": "player", "popular_name": "Stirling", "portrait_alt_id": "1", "portrait_object_id": "862319", "status_id": "3"}, {"age_days": "15", "age_years": "29", "alpha_name": "BALBIRNIE,A", "batting_hand": "right-hand batsman", "batting_style": "rhb", "batting_style_long": "right-hand bat", "bowling_hand": "right-arm bowler", "bowling_pacespin": "spin bowler", "bowling_style": "ob", "bowling_style_long": "right-arm offbreak ", "captain": "1", "card_long": "A Balbirnie", "card_qualifier": "", "card_short": "Balbirnie", "dob": "1990-12-28", "keeper": "0", "known_as": "Andy Balbirnie", "mobile_name": "Balbirnie", "object_id": "303423", "player_id": "52628", "player_primary_role": "opening batsman", "player_style_id": "1", "player_type": "1", "player_type_name": "player", "popular_name": "Andrew", "portrait_alt_id": "1", "portrait_object_id": "733223", "status_id": "3"}, {"age_days": "128", "age_years": "35", "alpha_name": "PORTERFIELD,WTS", "batting_hand": "left-hand batsman", "batting_style": "lhb", "batting_style_long": "left-hand bat", "bowling_hand": "right-arm bowler", "bowling_pacespin": "spin bowler", "bowling_style": "ob", "bowling_style_long": "right-arm offbreak ", "captain": "0", "card_long": "WTS Porterfield", "card_qualifier": "", "card_short": "Porterfield", "dob": "1984-09-06", "keeper": "0", "known_as": "William Porterfield", "mobile_name": "Porterfield", "object_id": "24611", "player_id": "47403", "player_primary_role": "opening batsman", "player_style_id": "1", "player_type": "1", "player_type_name": "player", "popular_name": "William", "portrait_alt_id": "", "portrait_object_id": "726979", "status_id": "3"}, {"age_days": "314", "age_years": "35", "alpha_name": "OBRIEN,KJ", "batting_hand": "right-hand batsman", "batting_style": "rhb", "batting_style_long": "right-hand bat", "bowling_hand": "right-arm bowler", "bowling_pacespin": "pace bowler", "bowling_style": "rmf", "bowling_style_long": "right-arm medium-fast ", "captain": "0", "card_long": "KJ O'Brien", "card_qualifier": "", "card_short": "O'Brien", "dob": "1984-03-04", "keeper": "0", "known_as": "Kevin O'Brien", "mobile_name": "K O'Brien", "object_id": "24605", "player_id": "47397", "player_primary_role": "allrounder", "player_style_id": "5", "player_type": "1", "player_type_name": "player", "popular_name": "Kevin", "portrait_alt_id": "1", "portrait_object_id": "979067", "status_id": "3"}, {"age_days": "124", "age_years": "23", "alpha_name": "TUCKER,LJ", "batting_hand": "right-hand batsman", "batting_style": "rhb", "batting_style_long": "right-hand bat", "bowling_hand": "unknown arm", "bowling_pacespin": "mixture/unknown", "bowling_style": null, "bowling_style_long": null, "captain": "0", "card_long": "LJ Tucker", "card_qualifier": "", "card_short": "Tucker", "dob": "1996-09-10", "keeper": "1", "known_as": "Lorcan Tucker", "mobile_name": "Tucker", "object_id": "928057", "player_id": "85965", "player_primary_role": "wicketkeeper batsman", "player_style_id": "7", "player_type": "1", "player_type_name": "player", "popular_name": "Tucker", "portrait_alt_id": "1", "portrait_object_id": "1176653", "status_id": "3"}, {"age_days": "342", "age_years": "32", "alpha_name": "SIMI_SINGH", "batting_hand": "right-hand batsman", "batting_style": "rhb", "batting_style_long": "right-hand bat", "bowling_hand": "right-arm bowler", "bowling_pacespin": "spin bowler", "bowling_style": "ob", "bowling_style_long": "right-arm offbreak ", "captain": "0", "card_long": "Simi Singh", "card_qualifier": "", "card_short": "Simi Singh", "dob": "1987-02-04", "keeper": "0", "known_as": "Simi Singh", "mobile_name": "Simi Singh", "object_id": "1005257", "player_id": "91741", "player_primary_role": "middle-order batsman", "player_style_id": "3", "player_type": "1", "player_type_name": "player", "popular_name": "", "portrait_alt_id": "1", "portrait_object_id": "1176652", "status_id": "3"}, {"age_days": "291", "age_years": "23", "alpha_name": "ADAIR,MR", "batting_hand": "right-hand batsman", "batting_style": "rhb", "batting_style_long": "right-hand bat", "bowling_hand": "right-arm bowler", "bowling_pacespin": "pace bowler", "bowling_style": "rf", "bowling_style_long": "right-arm fast ", "captain": "0", "card_long": "MR Adair", "card_qualifier": "", "card_short": "Adair", "dob": "1996-03-27", "keeper": "0", "known_as": "Mark Adair", "mobile_name": "Adair", "object_id": "526441", "player_id": "66012", "player_primary_role": "allrounder", "player_style_id": "5", "player_type": "1", "player_type_name": "player", "popular_name": "Adair", "portrait_alt_id": "1", "portrait_object_id": "895741", "status_id": "3"}, {"age_days": "257", "age_years": "26", "alpha_name": "MACBRINE,AR", "batting_hand": "left-hand batsman", "batting_style": "lhb", "batting_style_long": "left-hand bat", "bowling_hand": "right-arm bowler", "bowling_pacespin": "spin bowler", "bowling_style": "ob", "bowling_style_long": "right-arm offbreak ", "captain": "0", "card_long": "AR McBrine", "card_qualifier": "", "card_short": "McBrine", "dob": "1993-04-30", "keeper": "0", "known_as": "Andy McBrine", "mobile_name": "McBrine", "object_id": "417381", "player_id": "60322", "player_primary_role": "bowler", "player_style_id": "4", "player_type": "1", "player_type_name": "player", "popular_name": "McBrine", "portrait_alt_id": "", "portrait_object_id": "726985", "status_id": "3"}, {"age_days": "121", "age_years": "27", "alpha_name": "MCCARTHY,BJ", "batting_hand": "right-hand batsman", "batting_style": "rhb", "batting_style_long": "right-hand bat", "bowling_hand": "right-arm bowler", "bowling_pacespin": "pace bowler", "bowling_style": "rm", "bowling_style_long": "right-arm medium ", "captain": "0", "card_long": "BJ McCarthy", "card_qualifier": "", "card_short": "McCarthy", "dob": "1992-09-13", "keeper": "0", "known_as": "Barry McCarthy", "mobile_name": "McCarthy", "object_id": "348059", "player_id": "56835", "player_primary_role": "bowler", "player_style_id": "4", "player_type": "1", "player_type_name": "player", "popular_name": "McCarthy", "portrait_alt_id": "1", "portrait_object_id": "575837", "status_id": "3"}, {"age_days": "283", "age_years": "29", "alpha_name": "YOUNG,CA", "batting_hand": "right-hand batsman", "batting_style": "rhb", "batting_style_long": "right-hand bat", "bowling_hand": "right-arm bowler", "bowling_pacespin": "pace bowler", "bowling_style": "rfm", "bowling_style_long": "right-arm fast-medium ", "captain": "0", "card_long": "CA Young", "card_qualifier": "", "card_short": "Young", "dob": "1990-04-04", "keeper": "0", "known_as": "Craig Young", "mobile_name": "Young", "object_id": "364343", "player_id": "57785", "player_primary_role": "bowler", "player_style_id": "4", "player_type": "1", "player_type_name": "player", "popular_name": "Young", "portrait_alt_id": "1", "portrait_object_id": "728839", "status_id": "3"}], "roster_list": ["JA McCollum", "PR Stirling", "A Balbirnie", "WTS Porterfield", "KJ O'Brien", "LJ Tucker", "Simi Singh", "MR Adair", "AR McBrine", "BJ McCarthy", "CA Young"]}}