{"team_1": {"team_name": "Australia", "athlete_info_list": [{"age_days": "138", "age_years": "33", "alpha_name": "WARNER,DA", "batting_hand": "left-hand batsman", "batting_style": "lhb", "batting_style_long": "left-hand bat", "bowling_hand": "right-arm bowler", "bowling_pacespin": "spin bowler", "bowling_style": "lb", "bowling_style_long": "legbreak ", "captain": "0", "card_long": "DA Warner", "card_qualifier": "", "card_short": "Warner", "dob": "1986-10-27", "keeper": "0", "known_as": "David Warner", "mobile_name": "Warner", "object_id": "219889", "player_id": "48739", "player_primary_role": "opening batsman", "player_style_id": "1", "player_type": "1", "player_type_name": "player", "popular_name": "Warner", "portrait_alt_id": "1", "portrait_object_id": "1099532", "status_id": "3"}, {"age_days": "117", "age_years": "33", "alpha_name": "FINCH,AJ", "batting_hand": "right-hand batsman", "batting_style": "rhb", "batting_style_long": "right-hand bat", "bowling_hand": "left-arm bowler", "bowling_pacespin": "spin bowler", "bowling_style": "sla", "bowling_style_long": "slow left-arm orthodox ", "captain": "1", "card_long": "AJ Finch", "card_qualifier": "", "card_short": "Finch", "dob": "1986-11-17", "keeper": "0", "known_as": "Aaron Finch", "mobile_name": "Finch", "object_id": "5334", "player_id": "35812", "player_primary_role": "top-order batsman", "player_style_id": "2", "player_type": "1", "player_type_name": "player", "popular_name": "Finch", "portrait_alt_id": "1", "portrait_object_id": "1099503", "status_id": "3"}, {"age_days": "285", "age_years": "30", "alpha_name": "SMITH,SPD", "batting_hand": "right-hand batsman", "batting_style": "rhb", "batting_style_long": "right-hand bat", "bowling_hand": "right-arm bowler", "bowling_pacespin": "spin bowler", "bowling_style": "lbg", "bowling_style_long": "legbreak googly ", "captain": "0", "card_long": "SPD Smith", "card_qualifier": "", "card_short": "Smith", "dob": "1989-06-02", "keeper": "0", "known_as": "Steven Smith", "mobile_name": "Smith", "object_id": "267192", "player_id": "50281", "player_primary_role": "middle-order batsman", "player_style_id": "3", "player_type": "1", "player_type_name": "player", "popular_name": "Smith", "portrait_alt_id": "1", "portrait_object_id": "1099508", "status_id": "3"}, {"age_days": "217", "age_years": "29", "alpha_name": "SHORT,DJM", "batting_hand": "left-hand batsman", "batting_style": "lhb", "batting_style_long": "left-hand bat", "bowling_hand": "left-arm bowler", "bowling_pacespin": "spin bowler", "bowling_style": "slc", "bowling_style_long": "slow left-arm chinaman ", "captain": "0", "card_long": "DJM Short", "card_qualifier": "", "card_short": "Short", "dob": "1990-08-09", "keeper": "0", "known_as": "D'Arcy Short", "mobile_name": "Short", "object_id": "308798", "player_id": "53268", "player_primary_role": "opening batsman", "player_style_id": "1", "player_type": "1", "player_type_name": "player", "popular_name": "Short", "portrait_alt_id": "1", "portrait_object_id": "1133220", "status_id": "3"}, {"age_days": "265", "age_years": "25", "alpha_name": "LABUSCHANGE,M", "batting_hand": "right-hand batsman", "batting_style": "rhb", "batting_style_long": "right-hand bat", "bowling_hand": "right-arm bowler", "bowling_pacespin": "spin bowler", "bowling_style": "lb", "bowling_style_long": "legbreak ", "captain": "0", "card_long": "M Labuschagne", "card_qualifier": "", "card_short": "Labuschagne", "dob": "1994-06-22", "keeper": "0", "known_as": "Marnus Labuschagne", "mobile_name": "", "object_id": "787987", "player_id": "78285", "player_primary_role": "batting allrounder", "player_style_id": "10", "player_type": "1", "player_type_name": "player", "popular_name": "", "portrait_alt_id": "1", "portrait_object_id": "1162108", "status_id": "3"}, {"age_days": "145", "age_years": "28", "alpha_name": "MARSH,MR", "batting_hand": "right-hand batsman", "batting_style": "rhb", "batting_style_long": "right-hand bat", "bowling_hand": "right-arm bowler", "bowling_pacespin": "pace bowler", "bowling_style": "rm", "bowling_style_long": "right-arm medium ", "captain": "0", "card_long": "MR Marsh", "card_qualifier": "", "card_short": "Marsh", "dob": "1991-10-20", "keeper": "0", "known_as": "Mitchell Marsh", "mobile_name": "Marsh", "object_id": "272450", "player_id": "50771", "player_primary_role": "allrounder", "player_style_id": "5", "player_type": "1", "player_type_name": "player", "popular_name": "M Marsh", "portrait_alt_id": "", "portrait_object_id": "1030003", "status_id": "3"}, {"age_days": "199", "age_years": "28", "alpha_name": "CAREY,AT", "batting_hand": "left-hand batsman", "batting_style": "lhb", "batting_style_long": "left-hand bat", "bowling_hand": "unknown arm", "bowling_pacespin": "mixture/unknown", "bowling_style": null, "bowling_style_long": null, "captain": "0", "card_long": "AT Carey", "card_qualifier": "", "card_short": "Carey", "dob": "1991-08-27", "keeper": "1", "known_as": "Alex Carey", "mobile_name": "Carey", "object_id": "326434", "player_id": "54314", "player_primary_role": "wicketkeeper batsman", "player_style_id": "7", "player_type": "1", "player_type_name": "player", "popular_name": "Carey", "portrait_alt_id": "", "portrait_object_id": "1186409", "status_id": "3"}, {"age_days": "310", "age_years": "26", "alpha_name": "CUMMINS,PJ", "batting_hand": "right-hand batsman", "batting_style": "rhb", "batting_style_long": "right-hand bat", "bowling_hand": "right-arm bowler", "bowling_pacespin": "pace bowler", "bowling_style": "rf", "bowling_style_long": "right-arm fast ", "captain": "0", "card_long": "PJ Cummins", "card_qualifier": "", "card_short": "Cummins", "dob": "1993-05-08", "keeper": "0", "known_as": "Pat Cummins", "mobile_name": "Cummins", "object_id": "489889", "player_id": "64244", "player_primary_role": "bowler", "player_style_id": "4", "player_type": "1", "player_type_name": "player", "popular_name": "Cummins", "portrait_alt_id": "1", "portrait_object_id": "1099509", "status_id": "3"}, {"age_days": "43", "age_years": "30", "alpha_name": "STARC,MA", "batting_hand": "left-hand batsman", "batting_style": "lhb", "batting_style_long": "left-hand bat", "bowling_hand": "left-arm bowler", "bowling_pacespin": "pace bowler", "bowling_style": "lf", "bowling_style_long": "left-arm fast ", "captain": "0", "card_long": "MA Starc", "card_qualifier": "", "card_short": "Starc", "dob": "1990-01-30", "keeper": "0", "known_as": "Mitchell Starc", "mobile_name": "Starc", "object_id": "311592", "player_id": "53330", "player_primary_role": "bowler", "player_style_id": "4", "player_type": "1", "player_type_name": "player", "popular_name": "Starc", "portrait_alt_id": "1", "portrait_object_id": "1099513", "status_id": "3"}, {"age_days": "348", "age_years": "27", "alpha_name": "ZAMPA,A", "batting_hand": "right-hand batsman", "batting_style": "rhb", "batting_style_long": "right-hand bat", "bowling_hand": "right-arm bowler", "bowling_pacespin": "spin bowler", "bowling_style": "lbg", "bowling_style_long": "legbreak googly ", "captain": "0", "card_long": "A Zampa", "card_qualifier": "", "card_short": "Zampa", "dob": "1992-03-31", "keeper": "0", "known_as": "Adam Zampa", "mobile_name": "Zampa", "object_id": "379504", "player_id": "58435", "player_primary_role": "bowler", "player_style_id": "4", "player_type": "1", "player_type_name": "player", "popular_name": "Zampa", "portrait_alt_id": "1", "portrait_object_id": "1099536", "status_id": "3"}, {"age_days": "65", "age_years": "29", "alpha_name": "HAZLEWOOD,JR", "batting_hand": "left-hand batsman", "batting_style": "lhb", "batting_style_long": "left-hand bat", "bowling_hand": "right-arm bowler", "bowling_pacespin": "pace bowler", "bowling_style": "rfm", "bowling_style_long": "right-arm fast-medium ", "captain": "0", "card_long": "JR Hazlewood", "card_qualifier": "", "card_short": "Hazlewood", "dob": "1991-01-08", "keeper": "0", "known_as": "Josh Hazlewood", "mobile_name": "Hazlewood", "object_id": "288284", "player_id": "51367", "player_primary_role": "bowler", "player_style_id": "4", "player_type": "1", "player_type_name": "player", "popular_name": "H'wood", "portrait_alt_id": "1", "portrait_object_id": "1099517", "status_id": "3"}], "roster_list": ["DA Warner", "AJ Finch", "SPD Smith", "DJM Short", "M Labuschagne", "MR Marsh", "AT Carey", "PJ Cummins", "MA Starc", "A Zampa", "JR Hazlewood"]}, "team_2": {"team_name": "New Zealand", "athlete_info_list": [{"age_days": "165", "age_years": "33", "alpha_name": "GUPTILL,MJ", "batting_hand": "right-hand batsman", "batting_style": "rhb", "batting_style_long": "right-hand bat", "bowling_hand": "right-arm bowler", "bowling_pacespin": "spin bowler", "bowling_style": "ob", "bowling_style_long": "right-arm offbreak ", "captain": "0", "card_long": "MJ Guptill", "card_qualifier": "", "card_short": "Guptill", "dob": "1986-09-30", "keeper": "0", "known_as": "Martin Guptill", "mobile_name": "Guptill", "object_id": "226492", "player_id": "48927", "player_primary_role": "opening batsman", "player_style_id": "1", "player_type": "1", "player_type_name": "player", "popular_name": "Guptill", "portrait_alt_id": "1", "portrait_object_id": "1099469", "status_id": "3"}, {"age_days": "119", "age_years": "28", "alpha_name": "NICHOLLS, HM", "batting_hand": "left-hand batsman", "batting_style": "lhb", "batting_style_long": "left-hand bat", "bowling_hand": "right-arm bowler", "bowling_pacespin": "spin bowler", "bowling_style": "ob", "bowling_style_long": "right-arm offbreak ", "captain": "0", "card_long": "HM Nicholls", "card_qualifier": "", "card_short": "Nicholls", "dob": "1991-11-15", "keeper": "0", "known_as": "Henry Nicholls", "mobile_name": "Nicholls", "object_id": "539511", "player_id": "66842", "player_primary_role": "top-order batsman", "player_style_id": "2", "player_type": "1", "player_type_name": "player", "popular_name": "Nicholls", "portrait_alt_id": "", "portrait_object_id": "986881", "status_id": "3"}, {"age_days": "218", "age_years": "29", "alpha_name": "WILLIAMSON,KS", "batting_hand": "right-hand batsman", "batting_style": "rhb", "batting_style_long": "right-hand bat", "bowling_hand": "right-arm bowler", "bowling_pacespin": "spin bowler", "bowling_style": "ob", "bowling_style_long": "right-arm offbreak ", "captain": "1", "card_long": "KS Williamson", "card_qualifier": "", "card_short": "Williamson", "dob": "1990-08-08", "keeper": "0", "known_as": "Kane Williamson", "mobile_name": "Williamson", "object_id": "277906", "player_id": "51088", "player_primary_role": "top-order batsman", "player_style_id": "2", "player_type": "1", "player_type_name": "player", "popular_name": "Kane", "portrait_alt_id": "1", "portrait_object_id": "1099457", "status_id": "3"}, {"age_days": "5", "age_years": "36", "alpha_name": "TAYLOR,LRPL", "batting_hand": "right-hand batsman", "batting_style": "rhb", "batting_style_long": "right-hand bat", "bowling_hand": "right-arm bowler", "bowling_pacespin": "spin bowler", "bowling_style": "ob", "bowling_style_long": "right-arm offbreak ", "captain": "0", "card_long": "LRPL Taylor", "card_qualifier": "", "card_short": "Taylor", "dob": "1984-03-08", "keeper": "0", "known_as": "Ross Taylor", "mobile_name": "Taylor", "object_id": "38699", "player_id": "44930", "player_primary_role": "middle-order batsman", "player_style_id": "3", "player_type": "1", "player_type_name": "player", "popular_name": "Taylor", "portrait_alt_id": "1", "portrait_object_id": "1099483", "status_id": "3"}, {"age_days": "346", "age_years": "27", "alpha_name": "LATHAM,TWM", "batting_hand": "left-hand batsman", "batting_style": "lhb", "batting_style_long": "left-hand bat", "bowling_hand": "right-arm bowler", "bowling_pacespin": "pace bowler", "bowling_style": "rm", "bowling_style_long": "right-arm medium ", "captain": "0", "card_long": "TWM Latham", "card_qualifier": "", "card_short": "Latham", "dob": "1992-04-02", "keeper": "1", "known_as": "Tom Latham", "mobile_name": "Latham", "object_id": "388802", "player_id": "59148", "player_primary_role": "wicketkeeper batsman", "player_style_id": "7", "player_type": "1", "player_type_name": "player", "popular_name": "Latham", "portrait_alt_id": "1", "portrait_object_id": "1099471", "status_id": "3"}, {"age_days": "178", "age_years": "29", "alpha_name": "NEESHAM,JDS", "batting_hand": "left-hand batsman", "batting_style": "lhb", "batting_style_long": "left-hand bat", "bowling_hand": "right-arm bowler", "bowling_pacespin": "pace bowler", "bowling_style": "rmf", "bowling_style_long": "right-arm medium-fast ", "captain": "0", "card_long": "JDS Neesham", "card_qualifier": "", "card_short": "Neesham", "dob": "1990-09-17", "keeper": "0", "known_as": "James Neesham", "mobile_name": "Neesham", "object_id": "355269", "player_id": "57196", "player_primary_role": "batting allrounder", "player_style_id": "10", "player_type": "1", "player_type_name": "player", "popular_name": "Neesham", "portrait_alt_id": "1", "portrait_object_id": "1099477", "status_id": "3"}, {"age_days": "235", "age_years": "33", "alpha_name": "DEGRANDHOMME,C", "batting_hand": "right-hand batsman", "batting_style": "rhb", "batting_style_long": "right-hand bat", "bowling_hand": "right-arm bowler", "bowling_pacespin": "pace bowler", "bowling_style": "rmf", "bowling_style_long": "right-arm medium-fast ", "captain": "0", "card_long": "C de Grandhomme", "card_qualifier": "", "card_short": "de Grandhomme", "dob": "1986-07-22", "keeper": "0", "known_as": "Colin de Grandhomme", "mobile_name": "Colin", "object_id": "55395", "player_id": "47231", "player_primary_role": "allrounder", "player_style_id": "5", "player_type": "1", "player_type_name": "player", "popular_name": "Colin", "portrait_alt_id": "1", "portrait_object_id": "1099468", "status_id": "3"}, {"age_days": "37", "age_years": "28", "alpha_name": "SANTNER,MJ", "batting_hand": "left-hand batsman", "batting_style": "lhb", "batting_style_long": "left-hand bat", "bowling_hand": "left-arm bowler", "bowling_pacespin": "spin bowler", "bowling_style": "sla", "bowling_style_long": "slow left-arm orthodox ", "captain": "0", "card_long": "MJ Santner", "card_qualifier": "", "card_short": "Santner", "dob": "1992-02-05", "keeper": "0", "known_as": "Mitchell Santner", "mobile_name": "Santner", "object_id": "502714", "player_id": "64864", "player_primary_role": "bowling allrounder", "player_style_id": "11", "player_type": "1", "player_type_name": "player", "popular_name": "Santner", "portrait_alt_id": "1", "portrait_object_id": "1099481", "status_id": "3"}, {"age_days": "134", "age_years": "27", "alpha_name": "SODHI,IS", "batting_hand": "right-hand batsman", "batting_style": "rhb", "batting_style_long": "right-hand bat", "bowling_hand": "right-arm bowler", "bowling_pacespin": "spin bowler", "bowling_style": "lb", "bowling_style_long": "legbreak ", "captain": "0", "card_long": "IS Sodhi", "card_qualifier": "", "card_short": "Sodhi", "dob": "1992-10-31", "keeper": "0", "known_as": "Ish Sodhi", "mobile_name": "Sodhi", "object_id": "559066", "player_id": "67586", "player_primary_role": "bowler", "player_style_id": "4", "player_type": "1", "player_type_name": "player", "popular_name": "Sodhi", "portrait_alt_id": "", "portrait_object_id": "988687", "status_id": "3"}, {"age_days": "274", "age_years": "28", "alpha_name": "FERGUSON,LH", "batting_hand": "right-hand batsman", "batting_style": "rhb", "batting_style_long": "right-hand bat", "bowling_hand": "right-arm bowler", "bowling_pacespin": "pace bowler", "bowling_style": "rf", "bowling_style_long": "right-arm fast ", "captain": "0", "card_long": "LH Ferguson", "card_qualifier": "", "card_short": "Ferguson", "dob": "1991-06-13", "keeper": "0", "known_as": "Lockie Ferguson", "mobile_name": "Ferguson", "object_id": "493773", "player_id": "64402", "player_primary_role": "bowler", "player_style_id": "4", "player_type": "1", "player_type_name": "player", "popular_name": "Ferguson", "portrait_alt_id": "1", "portrait_object_id": "1070100", "status_id": "3"}, {"age_days": "235", "age_years": "30", "alpha_name": "BOULT,TA", "batting_hand": "right-hand batsman", "batting_style": "rhb", "batting_style_long": "right-hand bat", "bowling_hand": "left-arm bowler", "bowling_pacespin": "pace bowler", "bowling_style": "lfm", "bowling_style_long": "left-arm fast-medium ", "captain": "0", "card_long": "TA Boult", "card_qualifier": "", "card_short": "Boult", "dob": "1989-07-22", "keeper": "0", "known_as": "Trent Boult", "mobile_name": "Boult", "object_id": "277912", "player_id": "51092", "player_primary_role": "bowler", "player_style_id": "4", "player_type": "1", "player_type_name": "player", "popular_name": "Boult", "portrait_alt_id": "21", "portrait_object_id": "1099464", "status_id": "3"}], "roster_list": ["MJ Guptill", "HM Nicholls", "KS Williamson", "LRPL Taylor", "TWM Latham", "JDS Neesham", "C de Grandhomme", "MJ Santner", "IS Sodhi", "LH Ferguson", "TA Boult"]}}